mokupdf/__init__.py
mokupdf/__main__.py
mokupdf/server.py
mokupdf-1.0.1.dist-info/licenses/LICENSE
mokupdf-1.0.1.dist-info/METADATA
mokupdf-1.0.1.dist-info/WHEEL
mokupdf-1.0.1.dist-info/entry_points.txt
mokupdf-1.0.1.dist-info/top_level.txt
mokupdf-1.0.1.dist-info/RECORD
