Metadata-Version: 2.4
Name: mokupdf
Version: 1.0.1
Summary: MCP-compatible PDF reading server with intelligent file search and extraction
Home-page: https://github.com/jameslovespancakes/mokupdf
Author: MokuPDF Team
Author-email: MokuPDF Team <mokupdf@example.com>
Maintainer-email: MokuPDF Team <mokupdf@example.com>
License: MIT
Project-URL: Homepage, https://github.com/jameslovespancakes/mokupdf
Project-URL: Documentation, https://github.com/jameslovespancakes/mokupdf#readme
Project-URL: Repository, https://github.com/jameslovespancakes/mokupdf
Project-URL: Issues, https://github.com/jameslovespancakes/mokupdf/issues
Keywords: pdf,mcp,model-context-protocol,ai,llm,claude,pdf-reader,text-extraction,image-extraction,smart-search
Classifier: Development Status :: 4 - Beta
Classifier: Intended Audience :: Developers
Classifier: Intended Audience :: End Users/Desktop
Classifier: Topic :: Software Development :: Libraries :: Python Modules
Classifier: Topic :: Text Processing :: General
Classifier: Topic :: Office/Business :: Office Suites
Classifier: Topic :: Scientific/Engineering :: Artificial Intelligence
Classifier: License :: OSI Approved :: MIT License
Classifier: Programming Language :: Python :: 3
Classifier: Programming Language :: Python :: 3.8
Classifier: Programming Language :: Python :: 3.9
Classifier: Programming Language :: Python :: 3.10
Classifier: Programming Language :: Python :: 3.11
Classifier: Programming Language :: Python :: 3.12
Classifier: Operating System :: OS Independent
Requires-Python: >=3.8
License-File: LICENSE
Requires-Dist: mcp>=1.2.0
Requires-Dist: PyMuPDF>=1.23.0
Requires-Dist: Pillow>=10.0.0
Provides-Extra: dev
Requires-Dist: pytest>=7.0.0; extra == "dev"
Requires-Dist: pytest-cov>=4.0.0; extra == "dev"
Requires-Dist: black>=23.0.0; extra == "dev"
Requires-Dist: flake8>=6.0.0; extra == "dev"
Requires-Dist: twine>=4.0.0; extra == "dev"
Requires-Dist: build>=0.10.0; extra == "dev"
Provides-Extra: ocr
Requires-Dist: pytesseract>=0.3.10; extra == "ocr"
Dynamic: author
Dynamic: home-page
Dynamic: license-file
Dynamic: requires-python
